{"cameraMode":{"drawMode":0,"name":"Shaded","section":"Shading Mode"},"sceneLighting":false,"audioPlay":false,"sceneViewState":{"m_AlwaysRefresh":false,"showFog":true,"showSkybox":false,"showFlares":true,"showImageEffects":true,"showParticleSystems":true,"showVisualEffectGraphs":true,"m_FxEnabled":true},"in2DMode":false,"pivot":{"x":0.0,"y":0.1599999964237213,"z":0.0},"rotation":{"x":-0.0007924250676296651,"y":-0.9841695427894592,"z":0.00442870706319809,"w":-0.1772865504026413},"size":1.8720771074295045,"orthographic":false}